.gitignore
.gitmodules
.travis.yml
.woodpecker.yaml
AUTHORS
CHANGES.rst
LICENSE
MANIFEST.in
README.rst
appveyor.yml
setup.cfg
setup.py
.circleci/config.yml
conda-recipe/bld.bat
conda-recipe/build.sh
conda-recipe/meta.yaml
examples/van_der_pol.ipynb
examples/van_der_pol.png
examples/van_der_pol.py
examples/tests/test_examples.py
external/anyode/LICENSE
external/anyode/cython_def/anyode.pxd
external/anyode/cython_def/anyode_numpy.pxd
external/anyode/include/anyode/anyode.hpp
external/anyode/include/anyode/anyode_blas_lapack.hpp
external/anyode/include/anyode/anyode_blasless.hpp
external/anyode/include/anyode/anyode_buffer.hpp
external/anyode/include/anyode/anyode_decomposition.hpp
external/anyode/include/anyode/anyode_decomposition_lapack.hpp
external/anyode/include/anyode/anyode_iterative.hpp
external/anyode/include/anyode/anyode_matrix.hpp
external/anyode/include/anyode/anyode_numpy.hpp
external/anyode/include/anyode/anyode_numpy_types.hpp
external/anyode/include/anyode/anyode_parallel.hpp
external/anyode/include/anyode/anyode_util.hpp
pygslodeiv2/__init__.py
pygslodeiv2/_config.py
pygslodeiv2/_gsl_odeiv2.cpp
pygslodeiv2/_gsl_odeiv2.pyx
pygslodeiv2/_release.py
pygslodeiv2/_util.py
pygslodeiv2.egg-info/PKG-INFO
pygslodeiv2.egg-info/SOURCES.txt
pygslodeiv2.egg-info/dependency_links.txt
pygslodeiv2.egg-info/requires.txt
pygslodeiv2.egg-info/top_level.txt
pygslodeiv2/include/gsl_odeiv2_anyode.hpp
pygslodeiv2/include/gsl_odeiv2_anyode.pxd
pygslodeiv2/include/gsl_odeiv2_anyode_nogil.pxd
pygslodeiv2/include/gsl_odeiv2_anyode_parallel.hpp
pygslodeiv2/include/gsl_odeiv2_anyode_parallel.pxd
pygslodeiv2/include/gsl_odeiv2_cxx.hpp
pygslodeiv2/include/gsl_odeiv2_cxx.pxd
pygslodeiv2/tests/__init__.py
pygslodeiv2/tests/test_gsl_odeiv2.py
scripts/build_conda_recipe.sh
scripts/check_clean_repo_on_master.sh
scripts/ci.sh
scripts/coverage_badge.py
scripts/generate_docs.sh
scripts/post_release.sh
scripts/prepare_deploy.sh
scripts/rasterize.js
scripts/release.sh
scripts/render_index.sh
scripts/render_notebooks.sh
scripts/run_tests.sh
scripts/update-gh-pages.sh
tests/Makefile
tests/_gsl_odeiv2_anyode.pyx
tests/_gsl_odeiv2_anyode.pyxbld
