Metadata-Version: 2.4
Name: pygslodeiv2
Version: 0.9.7
Summary: Python binding for odeiv2 in GNU Scientific Library (GSL).
Home-page: https://github.com/bjodah/pygslodeiv2
Author: Bjoern I. Dahlgren
Author-email: bjodah@gmail.com
License: GPL-3.0
Classifier: Development Status :: 4 - Beta
Classifier: License :: OSI Approved :: GNU General Public License v3 (GPLv3)
Classifier: Operating System :: OS Independent
Classifier: Topic :: Scientific/Engineering
Classifier: Topic :: Scientific/Engineering :: Mathematics
License-File: LICENSE
License-File: AUTHORS
Requires-Dist: numpy
Requires-Dist: cython
Provides-Extra: docs
Requires-Dist: Sphinx; extra == "docs"
Requires-Dist: sphinx_rtd_theme; extra == "docs"
Requires-Dist: numpydoc; extra == "docs"
Dynamic: author
Dynamic: author-email
Dynamic: classifier
Dynamic: description
Dynamic: home-page
Dynamic: license
Dynamic: license-file
Dynamic: provides-extra
Dynamic: requires-dist
Dynamic: summary
